{
  "signUpData": [
    {
      "firstname": "Kartik",
      "lastname": "Jain",
      "email": "knjain@gmail.com",
      "phone": "9810776999",
      "dateofbirth": "1995-01-11T18:30:00.000Z",
      "password": "password",
      "newsletterintent": true,
      "id": "59f6"
    },
    {
      "firstname": "Neysa",
      "lastname": "Di Iorio",
      "email": "ndiiorio0@icio.us",
      "phone": "6604994144",
      "dateofbirth": "2004-12-14T07:29:45Z",
      "password": "nC4~c}x8$zAf",
      "newsletterintent": true,
      "id": "ZH6W"
    },
    {
      "firstname": "Hillary",
      "lastname": "Rasher",
      "email": "hrasher1@craigslist.org",
      "phone": "7971573051",
      "dateofbirth": "2020-10-13T18:30:00.000Z",
      "password": "mF1`\\Jh,Gp}",
      "newsletterintent": true,
      "id": "9LAK"
    },
    {
      "firstname": "Karena",
      "lastname": "Choulerton",
      "email": "kchoulerton2@t.co",
      "phone": "7237753631",
      "dateofbirth": "2008-08-11T09:20:22Z",
      "password": "mL5_R7",
      "newsletterintent": true,
      "id": "2AIS"
    },
    {
      "firstname": "Pernell",
      "lastname": "DeHooge",
      "email": "pdehooge3@discovery.com",
      "phone": "7025782203",
      "dateofbirth": "2013-06-29T17:46:00Z",
      "password": "cW8*,!B{_r",
      "newsletterintent": false,
      "id": "M4KA"
    },
    {
      "firstname": "Isadora",
      "lastname": "Deporte",
      "email": "ideporte4@europa.eu",
      "phone": "8576841866",
      "dateofbirth": "2001-09-20T07:33:04Z",
      "password": "bR1(va",
      "newsletterintent": false,
      "id": "GNI7"
    },
    {
      "firstname": "Rhodie",
      "lastname": "Kyttor",
      "email": "rkyttor5@bloomberg.com",
      "phone": "6452159629",
      "dateofbirth": "1998-06-05T07:43:19Z",
      "password": "rO9>+)K*wT",
      "newsletterintent": true,
      "id": "6KHZ"
    },
    {
      "firstname": "Lilith",
      "lastname": "Langrick",
      "email": "llangrick7@berkeley.edu",
      "phone": "3788451154",
      "dateofbirth": "2022-08-11T06:55:26Z",
      "password": "nQ1.QViW&",
      "newsletterintent": false,
      "id": "GH62"
    },
    {
      "firstname": "Deedee",
      "lastname": "Dockerty",
      "email": "ddockerty8@wisc.edu",
      "phone": "3694099556",
      "dateofbirth": "2009-07-26T20:04:08Z",
      "password": "bQ4,.A5",
      "newsletterintent": true,
      "id": "48SH"
    },
    {
      "firstname": "Peter",
      "lastname": "Parker",
      "email": "spiderman@avenger.com",
      "phone": "9999999993",
      "dateofbirth": "1969-06-08T18:30:00.000Z",
      "password": "spiderman",
      "newsletterintent": true,
      "id": "231a"
    }
  ]
}